[
  {
    "id":         "casa-naga-sayulita",
    "nombre":     "Casa Naga",
    "zona":       "bahia",
    "ubicacion":  "Sayulita, Nayarit",
    "recamaras":  5,
    "banos":      5,
    "m2":         null,
    "precio":     4000,
    "foto":       "assets/casa-naga-thumb.jpg",
    "url":        "propiedades/casa-naga-sayulita.html",
    "destacada":  true,
    "amenidades": ["Piscina infinita climatizada", "Chef personal", "Vista al Pacífico"]
  },
  {
    "id":         "casa-cielo-azul",
    "nombre":     "Casa Cielo Azul",
    "zona":       "bahia",
    "ubicacion":  "Bucerias, Bahía de Banderas",
    "recamaras":  5,
    "banos":      6,
    "m2":         650,
    "precio":     12000,
    "foto":       "https://images.unsplash.com/photo-1613490493576-7fde63acd811?w=700&q=80",
    "url":        "propiedades/casa-cielo-azul.html",
    "destacada":  true,
    "amenidades": ["Alberca infinita", "Playa privada", "Jacuzzi"]
  },
  {
    "id":         "villa-palmeras",
    "nombre":     "Villa Palmeras",
    "zona":       "vallarta",
    "ubicacion":  "Conchas Chinas, Puerto Vallarta",
    "recamaras":  4,
    "banos":      4,
    "m2":         420,
    "precio":     8500,
    "foto":       "https://images.unsplash.com/photo-1600585154340-be6161a56a0c?w=700&q=80",
    "url":        "propiedades/villa-palmeras.html",
    "destacada":  true,
    "amenidades": ["Alberca", "Vista al mar", "Jardín"]
  },
  {
    "id":         "penthouse-marina",
    "nombre":     "Penthouse Marina",
    "zona":       "vallarta",
    "ubicacion":  "Marina, Puerto Vallarta",
    "recamaras":  3,
    "banos":      3,
    "m2":         280,
    "precio":     5200,
    "foto":       "https://images.unsplash.com/photo-1571003123894-1f0594d2b5d9?w=700&q=80",
    "url":        "propiedades/penthouse-marina.html",
    "destacada":  true,
    "amenidades": ["Rooftop", "Vista 360°", "Gym"]
  },
  {
    "id":         "hacienda-punta-mita",
    "nombre":     "Hacienda Punta Mita",
    "zona":       "bahia",
    "ubicacion":  "Punta Mita, Bahía de Banderas",
    "recamaras":  6,
    "banos":      7,
    "m2":         900,
    "precio":     18000,
    "foto":       "https://images.unsplash.com/photo-1512917774080-9991f1c4c750?w=700&q=80",
    "url":        "propiedades/hacienda-punta-mita.html",
    "destacada":  false,
    "amenidades": ["Cancha de tenis", "Playa", "Chef privado"]
  },
  {
    "id":         "casa-sayulita",
    "nombre":     "Casa Sayulita Surf",
    "zona":       "bahia",
    "ubicacion":  "Sayulita, Nayarit",
    "recamaras":  3,
    "banos":      2,
    "m2":         180,
    "precio":     3800,
    "foto":       "https://images.unsplash.com/photo-1600607687920-4e2a09cf159d?w=700&q=80",
    "url":        "propiedades/casa-sayulita.html",
    "destacada":  false,
    "amenidades": ["A 50m del mar", "Surf", "Terraza"]
  },
  {
    "id":         "departamento-zona-romantica",
    "nombre":     "Depto. Zona Romántica",
    "zona":       "vallarta",
    "ubicacion":  "Zona Romántica, Puerto Vallarta",
    "recamaras":  2,
    "banos":      2,
    "m2":         120,
    "precio":     2200,
    "foto":       "https://images.unsplash.com/photo-1564013799919-ab600027ffc6?w=700&q=80",
    "url":        "propiedades/depto-zona-romantica.html",
    "destacada":  false,
    "amenidades": ["Centro histórico", "Rooftop compartido", "A/C"]
  },
  {
    "id":         "villa-la-cruz",
    "nombre":     "Villa La Cruz",
    "zona":       "bahia",
    "ubicacion":  "La Cruz de Huanacaxtle, Nayarit",
    "recamaras":  4,
    "banos":      4,
    "m2":         380,
    "precio":     7200,
    "foto":       "https://images.unsplash.com/photo-1580587771525-78b9dba3b914?w=700&q=80",
    "url":        "propiedades/villa-la-cruz.html",
    "destacada":  false,
    "amenidades": ["Alberca", "Vista a la marina", "BBQ"]
  },
  {
    "id":         "casa-5ta",
    "nombre":     "Casa 5ª Avenida",
    "zona":       "vallarta",
    "ubicacion":  "5ª Avenida, Puerto Vallarta",
    "recamaras":  5,
    "banos":      5,
    "m2":         520,
    "precio":     9800,
    "foto":       "https://images.unsplash.com/photo-1600596542815-ffad4c1539a9?w=700&q=80",
    "url":        "propiedades/casa-5ta.html",
    "destacada":  false,
    "amenidades": ["Alberca privada", "Cocina gourmet", "Cine"]
  }
]
